CHANGELOG.txt
LICENSE.txt
MANIFEST.in
README.txt
setup.py
calc/__init__.py
eg2w3_g3wg343.egg-info/PKG-INFO
eg2w3_g3wg343.egg-info/SOURCES.txt
eg2w3_g3wg343.egg-info/dependency_links.txt
eg2w3_g3wg343.egg-info/top_level.txt