Metadata-Version: 1.1
Name: eg2w3-g3wg343
Version: 0.0.1
Summary: A very basic calculator
Home-page: UNKNOWN
Author: Joshua Lowe
Author-email: palmbestna@gmail.com
License: MIT
Keywords: calc
Platform: UNKNOWN
Classifier: Development Status :: 5 - Production/Stable
Classifier: Intended Audience :: Education
Classifier: Operating System :: Microsoft :: Windows :: Windows 10
Classifier: License :: OSI Approved :: MIT License
Classifier: Programming Language :: Python :: 3
